odoo/addons/stock_inventory_discrepancy/README.rst
odoo/addons/stock_inventory_discrepancy/__init__.py
odoo/addons/stock_inventory_discrepancy/__manifest__.py
odoo/addons/stock_inventory_discrepancy/i18n/cs_CZ.po
odoo/addons/stock_inventory_discrepancy/i18n/de.po
odoo/addons/stock_inventory_discrepancy/i18n/es.po
odoo/addons/stock_inventory_discrepancy/i18n/es_ES.po
odoo/addons/stock_inventory_discrepancy/i18n/fr.po
odoo/addons/stock_inventory_discrepancy/i18n/fr_FR.po
odoo/addons/stock_inventory_discrepancy/i18n/hr.po
odoo/addons/stock_inventory_discrepancy/i18n/it.po
odoo/addons/stock_inventory_discrepancy/i18n/nl.po
odoo/addons/stock_inventory_discrepancy/i18n/nl_NL.po
odoo/addons/stock_inventory_discrepancy/i18n/pt_BR.po
odoo/addons/stock_inventory_discrepancy/i18n/sl.po
odoo/addons/stock_inventory_discrepancy/i18n/stock_inventory_discrepancy.pot
odoo/addons/stock_inventory_discrepancy/i18n/tr_TR.po
odoo/addons/stock_inventory_discrepancy/i18n/zh_CN.po
odoo/addons/stock_inventory_discrepancy/models/__init__.py
odoo/addons/stock_inventory_discrepancy/models/res_company.py
odoo/addons/stock_inventory_discrepancy/models/res_config_settings.py
odoo/addons/stock_inventory_discrepancy/models/stock_location.py
odoo/addons/stock_inventory_discrepancy/models/stock_quant.py
odoo/addons/stock_inventory_discrepancy/models/stock_warehouse.py
odoo/addons/stock_inventory_discrepancy/readme/CONFIGURE.md
odoo/addons/stock_inventory_discrepancy/readme/CONTRIBUTORS.md
odoo/addons/stock_inventory_discrepancy/readme/DESCRIPTION.md
odoo/addons/stock_inventory_discrepancy/readme/USAGE.md
odoo/addons/stock_inventory_discrepancy/security/ir.model.access.csv
odoo/addons/stock_inventory_discrepancy/security/stock_inventory_discrepancy_security.xml
odoo/addons/stock_inventory_discrepancy/static/description/icon.png
odoo/addons/stock_inventory_discrepancy/static/description/index.html
odoo/addons/stock_inventory_discrepancy/tests/__init__.py
odoo_addon_stock_inventory_discrepancy-18.0.1.1.0.1.dist-info/METADATA
odoo_addon_stock_inventory_discrepancy-18.0.1.1.0.1.dist-info/WHEEL
odoo_addon_stock_inventory_discrepancy-18.0.1.1.0.1.dist-info/top_level.txt
odoo_addon_stock_inventory_discrepancy-18.0.1.1.0.1.dist-info/RECORD
